multipy/__init__.py
multipy/multipy.py
mltipy-0.1.0.dist-info/METADATA
mltipy-0.1.0.dist-info/WHEEL
mltipy-0.1.0.dist-info/RECORD
