Metadata-Version: 2.3
Name: mltipy
Version: 0.1.0
Summary: Multiplayer w/ Supabase Realtime Python
Requires-Python: >=3.11
Requires-Dist: realtime
Requires-Dist: websockets>=12.0
